litemongo/__init__.py
litemongo/client.py
litemongo/h5py_store.py
litemongo/pytables_store.py
litemongo/sqlite_store.py
litemongo/stores.py
litemongo/version.py
litemongo/_vendor/__init__.py
litemongo/_vendor/mongomock/LICENSE
litemongo/_vendor/mongomock/__init__.py
litemongo/_vendor/mongomock/__init__.pyi
litemongo/_vendor/mongomock/__version__.py
litemongo/_vendor/mongomock/aggregate.py
litemongo/_vendor/mongomock/codec_options.py
litemongo/_vendor/mongomock/collection.py
litemongo/_vendor/mongomock/command_cursor.py
litemongo/_vendor/mongomock/database.py
litemongo/_vendor/mongomock/filtering.py
litemongo/_vendor/mongomock/gridfs.py
litemongo/_vendor/mongomock/helpers.py
litemongo/_vendor/mongomock/mongo_client.py
litemongo/_vendor/mongomock/not_implemented.py
litemongo/_vendor/mongomock/object_id.py
litemongo/_vendor/mongomock/patch.py
litemongo/_vendor/mongomock/py.typed
litemongo/_vendor/mongomock/read_concern.py
litemongo/_vendor/mongomock/read_preferences.py
litemongo/_vendor/mongomock/results.py
litemongo/_vendor/mongomock/store.py
litemongo/_vendor/mongomock/thread.py
litemongo/_vendor/mongomock/write_concern.py
litemongo-0.1.4.dist-info/LICENSE
litemongo-0.1.4.dist-info/WHEEL
litemongo-0.1.4.dist-info/METADATA
litemongo-0.1.4.dist-info/RECORD
