Metadata-Version: 2.1
Name: litemongo
Version: 0.1.4
Summary: File based MongoDB server with pymongo compatible API.
Keywords: mongodb,database,sqlite,disk-based
Author-email: Martin Uhrin <martin.uhrin.10@ucl.ac.uk>
Requires-Python: >=3.7
Classifier: Development Status :: 5 - Production/Stable
Classifier: License :: OSI Approved :: GNU Lesser General Public License v3 or later (LGPLv3+)
Classifier: Operating System :: POSIX :: Linux
Classifier: Operating System :: MacOS :: MacOS X
Classifier: Programming Language :: Python
Classifier: Programming Language :: Python :: 3.7
Classifier: Programming Language :: Python :: 3.8
Classifier: Programming Language :: Python :: 3.9
Classifier: Programming Language :: Python :: 3.10
Classifier: Topic :: Scientific/Engineering
Requires-Dist: pymongo
Requires-Dist: setuptools
Requires-Dist: packaging
Requires-Dist: pytz
Requires-Dist: sentinels
Requires-Dist: h5py ; extra == "backends"
Requires-Dist: tables ; extra == "backends"
Requires-Dist: black[d] ; extra == "dev"
Requires-Dist: flit ; extra == "dev"
Requires-Dist: pre-commit ; extra == "dev"
Requires-Dist: pytest ; extra == "dev"
Provides-Extra: backends
Provides-Extra: dev
